{
  "editor:toggle-highlight": [
    {
      "modifiers": [
        "Mod",
        "Shift"
      ],
      "key": "H"
    }
  ],
  "command-palette:open": [
    {
      "modifiers": [
        "Mod",
        "Shift"
      ],
      "key": "P"
    }
  ],
  "global-search:open": [
    {
      "modifiers": [
        "Mod",
        "Shift"
      ],
      "key": "F"
    },
    {
      "modifiers": [
        "Mod",
        "Shift"
      ],
      "key": "O"
    }
  ],
  "editor:toggle-code": [
    {
      "modifiers": [
        "Mod",
        "Shift"
      ],
      "key": "C"
    }
  ],
  "editor:toggle-bold": [
    {
      "modifiers": [
        "Mod"
      ],
      "key": "B"
    }
  ],
  "app:toggle-left-sidebar": [
    {
      "modifiers": [
        "Mod",
        "Shift"
      ],
      "key": "B"
    }
  ],
  "file-explorer:open": [
    {
      "modifiers": [
        "Mod",
        "Shift"
      ],
      "key": "E"
    }
  ]
}